eummd/__init__.py
eummd/cppsrc/__init__.py
eummd/cppsrc/cppmethods.cpp
eummd/cppsrc/cppmethods.cpython-311-darwin.so
eummd/cppsrc/cppmethods.pyx
eummd/cppsrc/eummd.cpp
eummd/cppsrc/eummd.h
eummd/cppsrc/meammd.cpp
eummd/cppsrc/meammd.h
eummd/cppsrc/medianHeuristic.cpp
eummd/cppsrc/medianHeuristic.h
eummd/cppsrc/naive.cpp
eummd/cppsrc/naive.h
eummd/cppsrc/oldmeammd.cpp
tests/__init__.py
tests/test_eummd.py
eummd-0.0.2.dist-info/LICENSE
eummd-0.0.2.dist-info/METADATA
eummd-0.0.2.dist-info/WHEEL
eummd-0.0.2.dist-info/top_level.txt
eummd-0.0.2.dist-info/RECORD
