Metadata-Version: 2.1
Name: eummd
Version: 0.0.2
Summary: Computes maximum mean discrepancy two-sample test for univariate data using the Laplacian kernel. It is also possible to compute the p-value using permutations.
Home-page: https://github.com/pypa/eummd
Author: Dean Bodenham
Author-email: deanbodenhampkgs@gmail.com
Classifier: Programming Language :: Python :: 3
Classifier: License :: OSI Approved :: GNU General Public License v2 or later (GPLv2+)
Classifier: Operating System :: OS Independent
Requires-Python: >=3.6
License-File: LICENSE
Requires-Dist: scipy (>=1)
Requires-Dist: numpy (>=1)
